{
  "trigger": true,
  "modules": [
    "boilerplate-create-challenge"
  ],
  "parentResource": "blinkleanace65002",
  "functionName": "blinkleanace65002CreateAuthChallenge",
  "resourceName": "blinkleanace65002CreateAuthChallenge",
  "parentStack": "auth",
  "triggerEnvs": "[]",
  "triggerDir": "C:\\snapshot\\amplify-cli\\build\\node_modules\\@aws-amplify\\amplify-category-auth\\provider-utils\\awscloudformation\\triggers\\CreateAuthChallenge",
  "triggerTemplate": "CreateAuthChallenge.json.ejs",
  "triggerEventPath": "CreateAuthChallenge.event.json",
  "roleName": "blinkleanace65002CreateAuthChallenge",
  "skipEdit": true
}